[
    {
        "p_orderId": 237,
        "p_action": "BUY",
        "p_totalQuantity": 1.0,
        "p_orderType": "MKT",
        "p_lmtPrice": 0.0,
        "p_auxPrice": 0.0,
        "p_tif": "GTC",
        "p_outsideRth": false,
        "s_orderId": 238,
        "s_action": "SELL",
        "s_totalQuantity": 1.0,
        "s_orderType": "STP",
        "s_lmtPrice": 0.0,
        "s_auxPrice": 10.86,
        "s_tif": "GTC",
        "s_parentId": 237,
        "s_outsideRth": false,
        "t_orderId": 239,
        "t_action": "SELL",
        "t_totalQuantity": 1.0,
        "t_orderType": "LMT",
        "t_lmtPrice": 11.63,
        "t_auxPrice": 0.0,
        "t_tif": "GTC",
        "t_parentId": 237,
        "t_outsideRth": false
    },
    {
        "p_orderId": 241,
        "p_action": "BUY",
        "p_totalQuantity": 1.0,
        "p_orderType": "MKT",
        "p_lmtPrice": 0.0,
        "p_auxPrice": 0.0,
        "p_tif": "GTC",
        "p_outsideRth": false,
        "s_orderId": 242,
        "s_action": "SELL",
        "s_totalQuantity": 1.0,
        "s_orderType": "STP",
        "s_lmtPrice": 0.0,
        "s_auxPrice": 11.3,
        "s_tif": "GTC",
        "s_parentId": 241,
        "s_outsideRth": false,
        "t_orderId": 243,
        "t_action": "SELL",
        "t_totalQuantity": 1.0,
        "t_orderType": "LMT",
        "t_lmtPrice": 12.11,
        "t_auxPrice": 0.0,
        "t_tif": "GTC",
        "t_parentId": 241,
        "t_outsideRth": false
    }
]