[
    {
        "symbol": "XNDU",
        "gap": 5.82,
        "gap_perc": 17.80905752753978,
        "gap_treshold": 10.0,
        "date_prev": "2026-04-16 00:00:00",
        "close_prev": 32.68,
        "date_curr": "2026-04-17 00:00:00",
        "open_curr": 38.5,
        "threshold_reached": true
    },
    {
        "symbol": "SILC",
        "gap": 4.73,
        "gap_perc": 19.011254019292608,
        "gap_treshold": 10.0,
        "date_prev": "2026-04-16 00:00:00",
        "close_prev": 24.88,
        "date_curr": "2026-04-17 00:00:00",
        "open_curr": 29.61,
        "threshold_reached": true
    },
    {
        "symbol": "MGRT",
        "gap": 11.72999999999999,
        "gap_perc": 10.924839340597922,
        "gap_treshold": 10.0,
        "date_prev": "2026-04-16 00:00:00",
        "close_prev": 107.37,
        "date_curr": "2026-04-17 00:00:00",
        "open_curr": 119.1,
        "threshold_reached": true
    },
    {
        "symbol": "UAL",
        "gap": 7.849999999999994,
        "gap_perc": 8.260549300220976,
        "gap_treshold": 10.0,
        "date_prev": "2026-04-16 00:00:00",
        "close_prev": 95.03,
        "date_curr": "2026-04-17 00:00:00",
        "open_curr": 102.88,
        "threshold_reached": false
    },
    {
        "symbol": "SOUX",
        "gap": 1.620000000000001,
        "gap_perc": 8.14889336016097,
        "gap_treshold": 10.0,
        "date_prev": "2026-04-16 00:00:00",
        "close_prev": 19.88,
        "date_curr": "2026-04-17 00:00:00",
        "open_curr": 21.5,
        "threshold_reached": false
    },
    {
        "symbol": "PDDL",
        "gap": 1.8999999999999986,
        "gap_perc": 8.566275924256079,
        "gap_treshold": 10.0,
        "date_prev": "2026-04-16 00:00:00",
        "close_prev": 22.18,
        "date_curr": "2026-04-17 00:00:00",
        "open_curr": 24.08,
        "threshold_reached": false
    },
    {
        "symbol": "MSTX",
        "gap": 1.9399999999999977,
        "gap_perc": 7.153392330383472,
        "gap_treshold": 10.0,
        "date_prev": "2026-04-16 00:00:00",
        "close_prev": 27.12,
        "date_curr": "2026-04-17 00:00:00",
        "open_curr": 29.06,
        "threshold_reached": false
    },
    {
        "symbol": "ELVR",
        "gap": 4.920000000000002,
        "gap_perc": 7.281337871836617,
        "gap_treshold": 10.0,
        "date_prev": "2026-04-16 00:00:00",
        "close_prev": 67.57,
        "date_curr": "2026-04-17 00:00:00",
        "open_curr": 72.49,
        "threshold_reached": false
    },
    {
        "symbol": "HOOG",
        "gap": 1.9199999999999982,
        "gap_perc": 7.331042382588766,
        "gap_treshold": 10.0,
        "date_prev": "2026-04-16 00:00:00",
        "close_prev": 26.19,
        "date_curr": "2026-04-17 00:00:00",
        "open_curr": 28.11,
        "threshold_reached": false
    },
    {
        "symbol": "ASMU",
        "gap": 1.7200000000000024,
        "gap_perc": 7.356715141146289,
        "gap_treshold": 10.0,
        "date_prev": "2026-04-16 00:00:00",
        "close_prev": 23.38,
        "date_curr": "2026-04-17 00:00:00",
        "open_curr": 25.1,
        "threshold_reached": false
    },
    {
        "symbol": "ASMG",
        "gap": 2.5500000000000043,
        "gap_perc": 7.130872483221489,
        "gap_treshold": 10.0,
        "date_prev": "2026-04-16 00:00:00",
        "close_prev": 35.76,
        "date_curr": "2026-04-17 00:00:00",
        "open_curr": 38.31,
        "threshold_reached": false
    },
    {
        "symbol": "BEG",
        "gap": 3.25,
        "gap_perc": 6.045386904761905,
        "gap_treshold": 10.0,
        "date_prev": "2026-04-16 00:00:00",
        "close_prev": 53.76,
        "date_curr": "2026-04-17 00:00:00",
        "open_curr": 57.01,
        "threshold_reached": false
    },
    {
        "symbol": "ALGT",
        "gap": 5.390000000000001,
        "gap_perc": 6.396866840731071,
        "gap_treshold": 10.0,
        "date_prev": "2026-04-16 00:00:00",
        "close_prev": 84.26,
        "date_curr": "2026-04-17 00:00:00",
        "open_curr": 89.65,
        "threshold_reached": false
    },
    {
        "symbol": "RYAAY",
        "gap": 3.740000000000002,
        "gap_perc": 6.520223152022318,
        "gap_treshold": 10.0,
        "date_prev": "2026-04-16 00:00:00",
        "close_prev": 57.36,
        "date_curr": "2026-04-17 00:00:00",
        "open_curr": 61.1,
        "threshold_reached": false
    },
    {
        "symbol": "HOOX",
        "gap": 2.1099999999999994,
        "gap_perc": 7.135610415962122,
        "gap_treshold": 10.0,
        "date_prev": "2026-04-16 00:00:00",
        "close_prev": 29.57,
        "date_curr": "2026-04-17 00:00:00",
        "open_curr": 31.68,
        "threshold_reached": false
    },
    {
        "symbol": "AFRM",
        "gap": 3.770000000000003,
        "gap_perc": 6.253109968485658,
        "gap_treshold": 10.0,
        "date_prev": "2026-04-16 00:00:00",
        "close_prev": 60.29,
        "date_curr": "2026-04-17 00:00:00",
        "open_curr": 64.06,
        "threshold_reached": false
    },
    {
        "symbol": "OSCX",
        "gap": 2.1600000000000037,
        "gap_perc": 6.023424428332414,
        "gap_treshold": 10.0,
        "date_prev": "2026-04-16 00:00:00",
        "close_prev": 35.86,
        "date_curr": "2026-04-17 00:00:00",
        "open_curr": 38.02,
        "threshold_reached": false
    },
    {
        "symbol": "TERG",
        "gap": 2.8900000000000006,
        "gap_perc": 5.077301475755447,
        "gap_treshold": 10.0,
        "date_prev": "2026-04-16 00:00:00",
        "close_prev": 56.92,
        "date_curr": "2026-04-17 00:00:00",
        "open_curr": 59.81,
        "threshold_reached": false
    },
    {
        "symbol": "MST",
        "gap": 1.6000000000000014,
        "gap_perc": 6.097560975609762,
        "gap_treshold": 10.0,
        "date_prev": "2026-04-16 00:00:00",
        "close_prev": 26.24,
        "date_curr": "2026-04-17 00:00:00",
        "open_curr": 27.84,
        "threshold_reached": false
    },
    {
        "symbol": "TEM",
        "gap": 3.0,
        "gap_perc": 5.512679162072767,
        "gap_treshold": 10.0,
        "date_prev": "2026-04-16 00:00:00",
        "close_prev": 54.42,
        "date_curr": "2026-04-17 00:00:00",
        "open_curr": 57.42,
        "threshold_reached": false
    },
    {
        "symbol": "TARK",
        "gap": 2.25,
        "gap_perc": 4.921259842519685,
        "gap_treshold": 10.0,
        "date_prev": "2026-04-16 00:00:00",
        "close_prev": 45.72,
        "date_curr": "2026-04-17 00:00:00",
        "open_curr": 47.97,
        "threshold_reached": false
    },
    {
        "symbol": "TSMG",
        "gap": 1.620000000000001,
        "gap_perc": 5.139593908629444,
        "gap_treshold": 10.0,
        "date_prev": "2026-04-16 00:00:00",
        "close_prev": 31.52,
        "date_curr": "2026-04-17 00:00:00",
        "open_curr": 33.14,
        "threshold_reached": false
    },
    {
        "symbol": "TSMU",
        "gap": 2.8000000000000043,
        "gap_perc": 4.8653344917463155,
        "gap_treshold": 10.0,
        "date_prev": "2026-04-16 00:00:00",
        "close_prev": 57.55,
        "date_curr": "2026-04-17 00:00:00",
        "open_curr": 60.35,
        "threshold_reached": false
    },
    {
        "symbol": "ORCX",
        "gap": 1.9499999999999957,
        "gap_perc": 5.062305295950145,
        "gap_treshold": 10.0,
        "date_prev": "2026-04-16 00:00:00",
        "close_prev": 38.52,
        "date_curr": "2026-04-17 00:00:00",
        "open_curr": 40.47,
        "threshold_reached": false
    },
    {
        "symbol": "APPX",
        "gap": 1.8799999999999955,
        "gap_perc": 5.147864184008749,
        "gap_treshold": 10.0,
        "date_prev": "2026-04-16 00:00:00",
        "close_prev": 36.52,
        "date_curr": "2026-04-17 00:00:00",
        "open_curr": 38.4,
        "threshold_reached": false
    },
    {
        "symbol": "LIF",
        "gap": 2.3200000000000003,
        "gap_perc": 5.039096437880105,
        "gap_treshold": 10.0,
        "date_prev": "2026-04-16 00:00:00",
        "close_prev": 46.04,
        "date_curr": "2026-04-17 00:00:00",
        "open_curr": 48.36,
        "threshold_reached": false
    },
    {
        "symbol": "SATG",
        "gap": 1.0600000000000023,
        "gap_perc": 5.0717703349282415,
        "gap_treshold": 10.0,
        "date_prev": "2026-04-16 00:00:00",
        "close_prev": 20.9,
        "date_curr": "2026-04-17 00:00:00",
        "open_curr": 21.96,
        "threshold_reached": false
    },
    {
        "symbol": "KLAG",
        "gap": 1.5800000000000018,
        "gap_perc": 5.594900849858364,
        "gap_treshold": 10.0,
        "date_prev": "2026-04-16 00:00:00",
        "close_prev": 28.24,
        "date_curr": "2026-04-17 00:00:00",
        "open_curr": 29.82,
        "threshold_reached": false
    },
    {
        "symbol": "HIMZ",
        "gap": 1.759999999999998,
        "gap_perc": 4.763193504736124,
        "gap_treshold": 10.0,
        "date_prev": "2026-04-16 00:00:00",
        "close_prev": 36.95,
        "date_curr": "2026-04-17 00:00:00",
        "open_curr": 38.71,
        "threshold_reached": false
    },
    {
        "symbol": "TSMX",
        "gap": 3.280000000000001,
        "gap_perc": 5.028361183504524,
        "gap_treshold": 10.0,
        "date_prev": "2026-04-16 00:00:00",
        "close_prev": 65.23,
        "date_curr": "2026-04-17 00:00:00",
        "open_curr": 68.51,
        "threshold_reached": false
    },
    {
        "symbol": "FORM",
        "gap": 6.030000000000001,
        "gap_perc": 4.721265267773255,
        "gap_treshold": 10.0,
        "date_prev": "2026-04-16 00:00:00",
        "close_prev": 127.72,
        "date_curr": "2026-04-17 00:00:00",
        "open_curr": 133.75,
        "threshold_reached": false
    },
    {
        "symbol": "KOD",
        "gap": 1.9500000000000028,
        "gap_perc": 4.826732673267334,
        "gap_treshold": 10.0,
        "date_prev": "2026-04-16 00:00:00",
        "close_prev": 40.4,
        "date_curr": "2026-04-17 00:00:00",
        "open_curr": 42.35,
        "threshold_reached": false
    },
    {
        "symbol": "AMZU",
        "gap": 1.6199999999999974,
        "gap_perc": 4.243059193294912,
        "gap_treshold": 10.0,
        "date_prev": "2026-04-16 00:00:00",
        "close_prev": 38.18,
        "date_curr": "2026-04-17 00:00:00",
        "open_curr": 39.8,
        "threshold_reached": false
    },
    {
        "symbol": "AMZZ",
        "gap": 1.5399999999999991,
        "gap_perc": 4.40755580995993,
        "gap_treshold": 10.0,
        "date_prev": "2026-04-16 00:00:00",
        "close_prev": 34.94,
        "date_curr": "2026-04-17 00:00:00",
        "open_curr": 36.48,
        "threshold_reached": false
    },
    {
        "symbol": "LGIH",
        "gap": 1.730000000000004,
        "gap_perc": 4.411014788373289,
        "gap_treshold": 10.0,
        "date_prev": "2026-04-16 00:00:00",
        "close_prev": 39.22,
        "date_curr": "2026-04-17 00:00:00",
        "open_curr": 40.95,
        "threshold_reached": false
    },
    {
        "symbol": "WWD",
        "gap": 15.660000000000025,
        "gap_perc": 4.17800544261246,
        "gap_treshold": 10.0,
        "date_prev": "2026-04-16 00:00:00",
        "close_prev": 374.82,
        "date_curr": "2026-04-17 00:00:00",
        "open_curr": 390.48,
        "threshold_reached": false
    },
    {
        "symbol": "HYDR",
        "gap": 1.7999999999999972,
        "gap_perc": 3.9352864013992064,
        "gap_treshold": 10.0,
        "date_prev": "2026-04-16 00:00:00",
        "close_prev": 45.74,
        "date_curr": "2026-04-17 00:00:00",
        "open_curr": 47.54,
        "threshold_reached": false
    },
    {
        "symbol": "BEAM",
        "gap": 1.3200000000000003,
        "gap_perc": 4.353562005277046,
        "gap_treshold": 10.0,
        "date_prev": "2026-04-16 00:00:00",
        "close_prev": 30.32,
        "date_curr": "2026-04-17 00:00:00",
        "open_curr": 31.64,
        "threshold_reached": false
    },
    {
        "symbol": "LMNX",
        "gap": 1.4400000000000013,
        "gap_perc": 6.8376068376068435,
        "gap_treshold": 10.0,
        "date_prev": "2026-04-16 00:00:00",
        "close_prev": 21.06,
        "date_curr": "2026-04-17 00:00:00",
        "open_curr": 22.5,
        "threshold_reached": false
    },
    {
        "symbol": "NBTX",
        "gap": 1.2800000000000011,
        "gap_perc": 3.9299969296899024,
        "gap_treshold": 10.0,
        "date_prev": "2026-04-16 00:00:00",
        "close_prev": 32.57,
        "date_curr": "2026-04-17 00:00:00",
        "open_curr": 33.85,
        "threshold_reached": false
    },
    {
        "symbol": "FFIN",
        "gap": 1.2999999999999972,
        "gap_perc": 4.198966408268725,
        "gap_treshold": 10.0,
        "date_prev": "2026-04-16 00:00:00",
        "close_prev": 30.96,
        "date_curr": "2026-04-17 00:00:00",
        "open_curr": 32.26,
        "threshold_reached": false
    },
    {
        "symbol": "ISSC",
        "gap": 0.9299999999999997,
        "gap_perc": 4.362101313320824,
        "gap_treshold": 10.0,
        "date_prev": "2026-04-16 00:00:00",
        "close_prev": 21.32,
        "date_curr": "2026-04-17 00:00:00",
        "open_curr": 22.25,
        "threshold_reached": false
    },
    {
        "symbol": "BANF",
        "gap": 4.489999999999995,
        "gap_perc": 4.015022802468027,
        "gap_treshold": 10.0,
        "date_prev": "2026-04-16 00:00:00",
        "close_prev": 111.83,
        "date_curr": "2026-04-17 00:00:00",
        "open_curr": 116.32,
        "threshold_reached": false
    },
    {
        "symbol": "STRO",
        "gap": 1.2800000000000011,
        "gap_perc": 4.370092181631961,
        "gap_treshold": 10.0,
        "date_prev": "2026-04-16 00:00:00",
        "close_prev": 29.29,
        "date_curr": "2026-04-17 00:00:00",
        "open_curr": 30.57,
        "threshold_reached": false
    },
    {
        "symbol": "MUU",
        "gap": 8.930000000000007,
        "gap_perc": 4.161230195712958,
        "gap_treshold": 10.0,
        "date_prev": "2026-04-16 00:00:00",
        "close_prev": 214.6,
        "date_curr": "2026-04-17 00:00:00",
        "open_curr": 223.53,
        "threshold_reached": false
    },
    {
        "symbol": "BOEU",
        "gap": 1.4500000000000028,
        "gap_perc": 3.995591071920647,
        "gap_treshold": 10.0,
        "date_prev": "2026-04-16 00:00:00",
        "close_prev": 36.29,
        "date_curr": "2026-04-17 00:00:00",
        "open_curr": 37.74,
        "threshold_reached": false
    },
    {
        "symbol": "TMDX",
        "gap": 4.47999999999999,
        "gap_perc": 4.106700889174067,
        "gap_treshold": 10.0,
        "date_prev": "2026-04-16 00:00:00",
        "close_prev": 109.09,
        "date_curr": "2026-04-17 00:00:00",
        "open_curr": 113.57,
        "threshold_reached": false
    },
    {
        "symbol": "MULL",
        "gap": 7.3300000000000125,
        "gap_perc": 3.8799491848401506,
        "gap_treshold": 10.0,
        "date_prev": "2026-04-16 00:00:00",
        "close_prev": 188.92,
        "date_curr": "2026-04-17 00:00:00",
        "open_curr": 196.25,
        "threshold_reached": false
    }
]